visionlock/__init__.py
visionlock/core.py
visionlock-0.2.1.dist-info/licenses/License
visionlock-0.2.1.dist-info/METADATA
visionlock-0.2.1.dist-info/WHEEL
visionlock-0.2.1.dist-info/top_level.txt
visionlock-0.2.1.dist-info/RECORD
