Metadata-Version: 2.4
Name: visionlock
Version: 0.2.1
Summary: A simple face-detection + ESP32 demo package for students.
Home-page: https://pypi.org/project/visionlock/
Author: Arjun
Author-email: Arjun <arjun@example.com>
License: MIT
Project-URL: Homepage, https://pypi.org/project/visionlock/
Requires-Python: >=3.7
License-File: License
Requires-Dist: opencv-python
Requires-Dist: face-recognition
Requires-Dist: pyserial
Requires-Dist: numpy
Requires-Dist: dlib-bin
Requires-Dist: cmake
Dynamic: license-file
